CredentialManager/__init__.py
CredentialManager/main.py
credentialmanager-0.0.3.dist-info/METADATA
credentialmanager-0.0.3.dist-info/WHEEL
credentialmanager-0.0.3.dist-info/top_level.txt
credentialmanager-0.0.3.dist-info/RECORD
